[
    {
        "team":"Arsenal",
        "players_used":26.0,
        "possession":59.3,
        "minutes_90s":38.0,
        "touches":25910.0,
        "touches_def_pen_area":1994.0,
        "touches_def_3rd":6632.0,
        "touches_mid_3rd":11453.0,
        "touches_att_3rd":8015.0,
        "touches_att_pen_area":1296.0,
        "touches_live_ball":25906.0,
        "take_ons":758.0,
        "take_ons_won":358.0,
        "take_ons_won_pct":47.2,
        "take_ons_tackled":290.0,
        "take_ons_tackled_pct":38.3,
        "carries":15923.0,
        "carries_distance":83916.0,
        "carries_progressive_distance":44184.0,
        "progressive_carries":824.0,
        "carries_into_final_third":584.0,
        "carries_into_penalty_area":281.0,
        "miscontrols":526.0,
        "dispossessed":378.0,
        "passes_received":18101.0,
        "progressive_passes_received":2024.0
    },
    {
        "team":"Aston Villa",
        "players_used":26.0,
        "possession":49.3,
        "minutes_90s":38.0,
        "touches":21500.0,
        "touches_def_pen_area":2783.0,
        "touches_def_3rd":7912.0,
        "touches_mid_3rd":9077.0,
        "touches_att_3rd":4705.0,
        "touches_att_pen_area":746.0,
        "touches_live_ball":21495.0,
        "take_ons":682.0,
        "take_ons_won":293.0,
        "take_ons_won_pct":43.0,
        "take_ons_tackled":279.0,
        "take_ons_tackled_pct":40.9,
        "carries":12295.0,
        "carries_distance":65580.0,
        "carries_progressive_distance":33150.0,
        "progressive_carries":637.0,
        "carries_into_final_third":434.0,
        "carries_into_penalty_area":174.0,
        "miscontrols":565.0,
        "dispossessed":371.0,
        "passes_received":13587.0,
        "progressive_passes_received":1227.0
    },
    {
        "team":"Bournemouth",
        "players_used":31.0,
        "possession":40.4,
        "minutes_90s":38.0,
        "touches":19950.0,
        "touches_def_pen_area":2934.0,
        "touches_def_3rd":8004.0,
        "touches_mid_3rd":7933.0,
        "touches_att_3rd":4256.0,
        "touches_att_pen_area":699.0,
        "touches_live_ball":19950.0,
        "take_ons":743.0,
        "take_ons_won":329.0,
        "take_ons_won_pct":44.3,
        "take_ons_tackled":344.0,
        "take_ons_tackled_pct":46.3,
        "carries":10340.0,
        "carries_distance":55360.0,
        "carries_progressive_distance":27431.0,
        "progressive_carries":504.0,
        "carries_into_final_third":389.0,
        "carries_into_penalty_area":144.0,
        "miscontrols":589.0,
        "dispossessed":367.0,
        "passes_received":11617.0,
        "progressive_passes_received":986.0
    },
    {
        "team":"Brentford",
        "players_used":25.0,
        "possession":43.8,
        "minutes_90s":38.0,
        "touches":19749.0,
        "touches_def_pen_area":2632.0,
        "touches_def_3rd":7290.0,
        "touches_mid_3rd":7803.0,
        "touches_att_3rd":4835.0,
        "touches_att_pen_area":827.0,
        "touches_live_ball":19741.0,
        "take_ons":600.0,
        "take_ons_won":267.0,
        "take_ons_won_pct":44.5,
        "take_ons_tackled":248.0,
        "take_ons_tackled_pct":41.3,
        "carries":10409.0,
        "carries_distance":49018.0,
        "carries_progressive_distance":23993.0,
        "progressive_carries":392.0,
        "carries_into_final_third":300.0,
        "carries_into_penalty_area":102.0,
        "miscontrols":520.0,
        "dispossessed":336.0,
        "passes_received":11203.0,
        "progressive_passes_received":1121.0
    },
    {
        "team":"Brighton",
        "players_used":29.0,
        "possession":60.2,
        "minutes_90s":38.0,
        "touches":26728.0,
        "touches_def_pen_area":2471.0,
        "touches_def_3rd":7844.0,
        "touches_mid_3rd":12213.0,
        "touches_att_3rd":6873.0,
        "touches_att_pen_area":1102.0,
        "touches_live_ball":26722.0,
        "take_ons":726.0,
        "take_ons_won":345.0,
        "take_ons_won_pct":47.5,
        "take_ons_tackled":279.0,
        "take_ons_tackled_pct":38.4,
        "carries":16331.0,
        "carries_distance":83718.0,
        "carries_progressive_distance":43965.0,
        "progressive_carries":809.0,
        "carries_into_final_third":547.0,
        "carries_into_penalty_area":250.0,
        "miscontrols":558.0,
        "dispossessed":324.0,
        "passes_received":18991.0,
        "progressive_passes_received":1828.0
    },
    {
        "team":"Chelsea",
        "players_used":32.0,
        "possession":58.7,
        "minutes_90s":38.0,
        "touches":27166.0,
        "touches_def_pen_area":2564.0,
        "touches_def_3rd":8461.0,
        "touches_mid_3rd":12057.0,
        "touches_att_3rd":6850.0,
        "touches_att_pen_area":958.0,
        "touches_live_ball":27163.0,
        "take_ons":838.0,
        "take_ons_won":380.0,
        "take_ons_won_pct":45.3,
        "take_ons_tackled":352.0,
        "take_ons_tackled_pct":42.0,
        "carries":16538.0,
        "carries_distance":83509.0,
        "carries_progressive_distance":43596.0,
        "progressive_carries":829.0,
        "carries_into_final_third":622.0,
        "carries_into_penalty_area":216.0,
        "miscontrols":568.0,
        "dispossessed":381.0,
        "passes_received":19065.0,
        "progressive_passes_received":1729.0
    },
    {
        "team":"Crystal Palace",
        "players_used":26.0,
        "possession":46.3,
        "minutes_90s":38.0,
        "touches":21713.0,
        "touches_def_pen_area":2580.0,
        "touches_def_3rd":7668.0,
        "touches_mid_3rd":9275.0,
        "touches_att_3rd":4991.0,
        "touches_att_pen_area":766.0,
        "touches_live_ball":21710.0,
        "take_ons":784.0,
        "take_ons_won":367.0,
        "take_ons_won_pct":46.8,
        "take_ons_tackled":314.0,
        "take_ons_tackled_pct":40.1,
        "carries":11687.0,
        "carries_distance":60301.0,
        "carries_progressive_distance":30015.0,
        "progressive_carries":556.0,
        "carries_into_final_third":393.0,
        "carries_into_penalty_area":206.0,
        "miscontrols":643.0,
        "dispossessed":457.0,
        "passes_received":13304.0,
        "progressive_passes_received":1238.0
    },
    {
        "team":"Everton",
        "players_used":28.0,
        "possession":42.8,
        "minutes_90s":38.0,
        "touches":20233.0,
        "touches_def_pen_area":2527.0,
        "touches_def_3rd":7219.0,
        "touches_mid_3rd":8418.0,
        "touches_att_3rd":4830.0,
        "touches_att_pen_area":742.0,
        "touches_live_ball":20229.0,
        "take_ons":674.0,
        "take_ons_won":310.0,
        "take_ons_won_pct":46.0,
        "take_ons_tackled":296.0,
        "take_ons_tackled_pct":43.9,
        "carries":10479.0,
        "carries_distance":56737.0,
        "carries_progressive_distance":27858.0,
        "progressive_carries":500.0,
        "carries_into_final_third":391.0,
        "carries_into_penalty_area":137.0,
        "miscontrols":605.0,
        "dispossessed":300.0,
        "passes_received":11708.0,
        "progressive_passes_received":1042.0
    },
    {
        "team":"Fulham",
        "players_used":29.0,
        "possession":48.8,
        "minutes_90s":38.0,
        "touches":22162.0,
        "touches_def_pen_area":2563.0,
        "touches_def_3rd":7462.0,
        "touches_mid_3rd":9525.0,
        "touches_att_3rd":5416.0,
        "touches_att_pen_area":758.0,
        "touches_live_ball":22153.0,
        "take_ons":607.0,
        "take_ons_won":281.0,
        "take_ons_won_pct":46.3,
        "take_ons_tackled":238.0,
        "take_ons_tackled_pct":39.2,
        "carries":12252.0,
        "carries_distance":68216.0,
        "carries_progressive_distance":35374.0,
        "progressive_carries":663.0,
        "carries_into_final_third":474.0,
        "carries_into_penalty_area":124.0,
        "miscontrols":535.0,
        "dispossessed":379.0,
        "passes_received":13848.0,
        "progressive_passes_received":1316.0
    },
    {
        "team":"Leeds United",
        "players_used":29.0,
        "possession":47.0,
        "minutes_90s":38.0,
        "touches":21642.0,
        "touches_def_pen_area":2125.0,
        "touches_def_3rd":6971.0,
        "touches_mid_3rd":9290.0,
        "touches_att_3rd":5587.0,
        "touches_att_pen_area":796.0,
        "touches_live_ball":21639.0,
        "take_ons":689.0,
        "take_ons_won":269.0,
        "take_ons_won_pct":39.0,
        "take_ons_tackled":328.0,
        "take_ons_tackled_pct":47.6,
        "carries":11343.0,
        "carries_distance":55029.0,
        "carries_progressive_distance":27060.0,
        "progressive_carries":555.0,
        "carries_into_final_third":379.0,
        "carries_into_penalty_area":146.0,
        "miscontrols":602.0,
        "dispossessed":421.0,
        "passes_received":12330.0,
        "progressive_passes_received":1418.0
    },
    {
        "team":"Leicester City",
        "players_used":28.0,
        "possession":47.7,
        "minutes_90s":38.0,
        "touches":23124.0,
        "touches_def_pen_area":2681.0,
        "touches_def_3rd":8409.0,
        "touches_mid_3rd":10293.0,
        "touches_att_3rd":4641.0,
        "touches_att_pen_area":688.0,
        "touches_live_ball":23118.0,
        "take_ons":623.0,
        "take_ons_won":294.0,
        "take_ons_won_pct":47.2,
        "take_ons_tackled":245.0,
        "take_ons_tackled_pct":39.3,
        "carries":12503.0,
        "carries_distance":63356.0,
        "carries_progressive_distance":31619.0,
        "progressive_carries":580.0,
        "carries_into_final_third":363.0,
        "carries_into_penalty_area":175.0,
        "miscontrols":548.0,
        "dispossessed":313.0,
        "passes_received":14797.0,
        "progressive_passes_received":1294.0
    },
    {
        "team":"Liverpool",
        "players_used":28.0,
        "possession":60.8,
        "minutes_90s":38.0,
        "touches":28398.0,
        "touches_def_pen_area":2310.0,
        "touches_def_3rd":8119.0,
        "touches_mid_3rd":13329.0,
        "touches_att_3rd":7149.0,
        "touches_att_pen_area":1252.0,
        "touches_live_ball":28394.0,
        "take_ons":693.0,
        "take_ons_won":323.0,
        "take_ons_won_pct":46.6,
        "take_ons_tackled":281.0,
        "take_ons_tackled_pct":40.5,
        "carries":17148.0,
        "carries_distance":82470.0,
        "carries_progressive_distance":41527.0,
        "progressive_carries":719.0,
        "carries_into_final_third":569.0,
        "carries_into_penalty_area":234.0,
        "miscontrols":584.0,
        "dispossessed":413.0,
        "passes_received":19921.0,
        "progressive_passes_received":1974.0
    },
    {
        "team":"Manchester City",
        "players_used":24.0,
        "possession":64.7,
        "minutes_90s":38.0,
        "touches":29895.0,
        "touches_def_pen_area":2170.0,
        "touches_def_3rd":7410.0,
        "touches_mid_3rd":14372.0,
        "touches_att_3rd":8301.0,
        "touches_att_pen_area":1277.0,
        "touches_live_ball":29885.0,
        "take_ons":704.0,
        "take_ons_won":336.0,
        "take_ons_won_pct":47.7,
        "take_ons_tackled":239.0,
        "take_ons_tackled_pct":33.9,
        "carries":19122.0,
        "carries_distance":104099.0,
        "carries_progressive_distance":56216.0,
        "progressive_carries":988.0,
        "carries_into_final_third":754.0,
        "carries_into_penalty_area":279.0,
        "miscontrols":406.0,
        "dispossessed":298.0,
        "passes_received":22992.0,
        "progressive_passes_received":2054.0
    },
    {
        "team":"Manchester Utd",
        "players_used":26.0,
        "possession":53.7,
        "minutes_90s":38.0,
        "touches":24847.0,
        "touches_def_pen_area":2639.0,
        "touches_def_3rd":8093.0,
        "touches_mid_3rd":10389.0,
        "touches_att_3rd":6569.0,
        "touches_att_pen_area":1036.0,
        "touches_live_ball":24844.0,
        "take_ons":730.0,
        "take_ons_won":317.0,
        "take_ons_won_pct":43.4,
        "take_ons_tackled":338.0,
        "take_ons_tackled_pct":46.3,
        "carries":14245.0,
        "carries_distance":70351.0,
        "carries_progressive_distance":37126.0,
        "progressive_carries":711.0,
        "carries_into_final_third":515.0,
        "carries_into_penalty_area":239.0,
        "miscontrols":497.0,
        "dispossessed":293.0,
        "passes_received":16447.0,
        "progressive_passes_received":1578.0
    },
    {
        "team":"Newcastle United",
        "players_used":27.0,
        "possession":52.3,
        "minutes_90s":38.0,
        "touches":22106.0,
        "touches_def_pen_area":2088.0,
        "touches_def_3rd":6757.0,
        "touches_mid_3rd":9053.0,
        "touches_att_3rd":6516.0,
        "touches_att_pen_area":1161.0,
        "touches_live_ball":22100.0,
        "take_ons":784.0,
        "take_ons_won":350.0,
        "take_ons_won_pct":44.6,
        "take_ons_tackled":322.0,
        "take_ons_tackled_pct":41.1,
        "carries":12023.0,
        "carries_distance":64186.0,
        "carries_progressive_distance":32987.0,
        "progressive_carries":695.0,
        "carries_into_final_third":493.0,
        "carries_into_penalty_area":228.0,
        "miscontrols":576.0,
        "dispossessed":363.0,
        "passes_received":13803.0,
        "progressive_passes_received":1599.0
    },
    {
        "team":"Nottingham Forest",
        "players_used":33.0,
        "possession":37.6,
        "minutes_90s":38.0,
        "touches":17911.0,
        "touches_def_pen_area":2715.0,
        "touches_def_3rd":7420.0,
        "touches_mid_3rd":6953.0,
        "touches_att_3rd":3755.0,
        "touches_att_pen_area":611.0,
        "touches_live_ball":17905.0,
        "take_ons":572.0,
        "take_ons_won":258.0,
        "take_ons_won_pct":45.1,
        "take_ons_tackled":234.0,
        "take_ons_tackled_pct":40.9,
        "carries":8674.0,
        "carries_distance":46411.0,
        "carries_progressive_distance":24020.0,
        "progressive_carries":436.0,
        "carries_into_final_third":308.0,
        "carries_into_penalty_area":111.0,
        "miscontrols":537.0,
        "dispossessed":275.0,
        "passes_received":9452.0,
        "progressive_passes_received":847.0
    },
    {
        "team":"Southampton",
        "players_used":36.0,
        "possession":44.5,
        "minutes_90s":38.0,
        "touches":21094.0,
        "touches_def_pen_area":2639.0,
        "touches_def_3rd":7453.0,
        "touches_mid_3rd":8997.0,
        "touches_att_3rd":4879.0,
        "touches_att_pen_area":712.0,
        "touches_live_ball":21090.0,
        "take_ons":760.0,
        "take_ons_won":362.0,
        "take_ons_won_pct":47.6,
        "take_ons_tackled":318.0,
        "take_ons_tackled_pct":41.8,
        "carries":11323.0,
        "carries_distance":61002.0,
        "carries_progressive_distance":29821.0,
        "progressive_carries":588.0,
        "carries_into_final_third":452.0,
        "carries_into_penalty_area":131.0,
        "miscontrols":567.0,
        "dispossessed":401.0,
        "passes_received":12216.0,
        "progressive_passes_received":1112.0
    },
    {
        "team":"Tottenham Hotspur",
        "players_used":29.0,
        "possession":50.0,
        "minutes_90s":38.0,
        "touches":23836.0,
        "touches_def_pen_area":2734.0,
        "touches_def_3rd":8571.0,
        "touches_mid_3rd":10329.0,
        "touches_att_3rd":5135.0,
        "touches_att_pen_area":842.0,
        "touches_live_ball":23830.0,
        "take_ons":666.0,
        "take_ons_won":306.0,
        "take_ons_won_pct":45.9,
        "take_ons_tackled":288.0,
        "take_ons_tackled_pct":43.2,
        "carries":13679.0,
        "carries_distance":71290.0,
        "carries_progressive_distance":36842.0,
        "progressive_carries":692.0,
        "carries_into_final_third":465.0,
        "carries_into_penalty_area":189.0,
        "miscontrols":521.0,
        "dispossessed":356.0,
        "passes_received":15864.0,
        "progressive_passes_received":1436.0
    },
    {
        "team":"West Ham United",
        "players_used":25.0,
        "possession":42.1,
        "minutes_90s":38.0,
        "touches":20411.0,
        "touches_def_pen_area":2362.0,
        "touches_def_3rd":6898.0,
        "touches_mid_3rd":8704.0,
        "touches_att_3rd":4993.0,
        "touches_att_pen_area":756.0,
        "touches_live_ball":20403.0,
        "take_ons":615.0,
        "take_ons_won":250.0,
        "take_ons_won_pct":40.7,
        "take_ons_tackled":266.0,
        "take_ons_tackled_pct":43.3,
        "carries":10540.0,
        "carries_distance":57451.0,
        "carries_progressive_distance":28247.0,
        "progressive_carries":615.0,
        "carries_into_final_third":413.0,
        "carries_into_penalty_area":166.0,
        "miscontrols":458.0,
        "dispossessed":357.0,
        "passes_received":12256.0,
        "progressive_passes_received":1266.0
    },
    {
        "team":"Wolves",
        "players_used":32.0,
        "possession":49.9,
        "minutes_90s":38.0,
        "touches":22539.0,
        "touches_def_pen_area":2921.0,
        "touches_def_3rd":8544.0,
        "touches_mid_3rd":9264.0,
        "touches_att_3rd":4960.0,
        "touches_att_pen_area":686.0,
        "touches_live_ball":22536.0,
        "take_ons":782.0,
        "take_ons_won":385.0,
        "take_ons_won_pct":49.2,
        "take_ons_tackled":302.0,
        "take_ons_tackled_pct":38.6,
        "carries":12374.0,
        "carries_distance":67241.0,
        "carries_progressive_distance":35071.0,
        "progressive_carries":610.0,
        "carries_into_final_third":421.0,
        "carries_into_penalty_area":142.0,
        "miscontrols":516.0,
        "dispossessed":326.0,
        "passes_received":14453.0,
        "progressive_passes_received":1332.0
    }
]